MANIFEST.in
README.md
setup.py
hackertray/__init__.py
hackertray/appindicator_replacement.py
hackertray/chrome.py
hackertray/firefox.py
hackertray/hackernews.py
hackertray/version.py
hackertray.egg-info/PKG-INFO
hackertray.egg-info/SOURCES.txt
hackertray.egg-info/dependency_links.txt
hackertray.egg-info/entry_points.txt
hackertray.egg-info/not-zip-safe
hackertray.egg-info/requires.txt
hackertray.egg-info/top_level.txt
hackertray/data/__init__.py
hackertray/data/hacker-tray.png