Metadata-Version: 1.0
Name: hackertray
Version: 4.0.0
Summary: Hacker News app that sits in your System Tray
Home-page: https://captnemo.in/hackertray
Author: Abhay Rana (Nemo)
Author-email: me@captnemo.in
License: MIT
Keywords: hacker news hn tray system tray icon hackertray
Platform: UNKNOWN
